upstash_ratelimit/__init__.py
upstash_ratelimit/asyncio/__init__.py
upstash_ratelimit/asyncio/ratelimit.py
upstash_ratelimit/limiter.py
upstash_ratelimit/py.typed
upstash_ratelimit/ratelimit.py
upstash_ratelimit/typing.py
upstash_ratelimit/utils.py
upstash_ratelimit-1.1.0.dist-info/LICENSE
upstash_ratelimit-1.1.0.dist-info/METADATA
upstash_ratelimit-1.1.0.dist-info/WHEEL
upstash_ratelimit-1.1.0.dist-info/RECORD
