Metadata-Version: 2.1
Name: upstash-ratelimit
Version: 1.1.0
Summary: Serverless ratelimiting package from Upstash
Home-page: https://github.com/upstash/ratelimit-python
Keywords: ratelimit,rate limit,Upstash rate limit,Redis rate limit
Author: Upstash
Author-email: support@upstash.com
Maintainer: Upstash
Maintainer-email: support@upstash.com
Requires-Python: >=3.8,<4.0
Classifier: Development Status :: 5 - Production/Stable
Classifier: Intended Audience :: Developers
Classifier: License :: OSI Approved :: MIT License
Classifier: Operating System :: OS Independent
Classifier: Programming Language :: Python
Classifier: Programming Language :: Python :: 3
Classifier: Programming Language :: Python :: 3.8
Classifier: Programming Language :: Python :: 3.9
Classifier: Programming Language :: Python :: 3.10
Classifier: Programming Language :: Python :: 3.11
Classifier: Programming Language :: Python :: 3.12
Classifier: Programming Language :: Python :: 3 :: Only
Classifier: Programming Language :: Python :: Implementation :: CPython
Classifier: Topic :: Software Development :: Libraries
Requires-Dist: upstash-redis (>=1.0.0,<2.0.0)
Project-URL: Repository, https://github.com/upstash/ratelimit-python
